Workbook

Sheet Year 2026
B3: Company N Year 2026 | C3: Initial Capital | D3: Jan-26 | E3: Feb-26 | F3: Mar-26 | G3: Apr-26 | H3: May-26 | I3: Jun-26 | J3: Jul-26 | K3: Aug-26 | L3: Sep-26 | M3: Oct-26 | N3: Nov-26 | O3: Dec-26 | P3: Total
B4: Opening Balance | D4: =C26 -> 0 | E4: =D26 -> 0 | F4: =E26 -> 0 | G4: =F26 -> 0 | H4: =G26 -> 0 | I4: =H26 -> 0 | J4: =I26 -> 0 | K4: =J26 -> 0 | ... O4: =N26 -> 0
B6: Revenue | D6: Jan-26 | E6: Feb-26 | F6: Mar-26 | G6: Apr-26 | H6: May-26 | I6: Jun-26 | J6: Jul-26 | K6: Aug-26 | L6: Sep-26 | M6: Oct-26 | N6: Nov-26 | O6: Dec-26 | P6: Total
B7: Cash Takings | D7: =January!C34 -> 0 | E7: =February!C34 -> 0 | F7: =March!C34 -> 0 | G7: =April!C34 -> 0 | H7: =May!C34 -> 0 | I7: =June!C34 -> 0 | J7: =July!C34 -> 0 | K7: =August!C34 -> 0 | L7: =September!C34 -> 0 | M7: =October!C34 -> 0 | N7: =November!C34 -> 0 | O7: =December!C34 -> 0 | P7: =SUM(Revenue[[#This Row],[Jan-26]:[Dec-26]]) -> 0
B8: E-POS | D8: =January!D34 -> 0 | E8: =February!D34 -> 0 | F8: =March!D34 -> 0 | G8: =April!D34 -> 0 | H8: =May!D34 -> 0 | I8: =June!D34 -> 0 | J8: =July!D34 -> 0 | K8: =August!D34 -> 0 | L8: =September!D34 -> 0 | M8: =October!D34 -> 0 | N8: =November!D34 -> 0 | O8: =December!D34 -> 0 | P8: =SUM(Revenue[[#This Row],[Jan-26]:[Dec-26]]) -> 0
B9: POS | D9: =January!E34 -> 0 | E9: =February!E34 -> 0 | F9: =March!E34 -> 0 | G9: =April!E34 -> 0 | H9: =May!E34 -> 0 | I9: =June!E34 -> 0 | J9: =July!E34 -> 0 | K9: =August!E34 -> 0 | L9: =September!E34 -> 0 | M9: =October!E34 -> 0 | N9: =November!E34 -> 0 | O9: =December!E34 -> 0 | P9: =SUM(Revenue[[#This Row],[Jan-26]:[Dec-26]]) -> 0
B10: Refunds | D10: =January!F34 -> 0 | E10: =February!F34 -> 0 | F10: =March!F34 -> 0 | G10: =April!F34 -> 0 | H10: =May!F34 -> 0 | I10: =June!F34 -> 0 | J10: =July!F34 -> 0 | K10: =August!F34 -> 0 | L10: =September!F34 -> 0 | M10: =October!F34 -> 0 | N10: =November!F34 -> 0 | O10: =December!F34 -> 0 | P10: =SUM(Revenue[[#This Row],[Jan-26]:[Dec-26]]) -> 0
B11: Net Revenue | D11: =SUM(D7:D9,(D10*-1)) -> 0 | E11: =SUM(E7:E9,(E10*-1)) -> 0 | F11: =SUM(F7:F9,(F10*-1)) -> 0 | G11: =SUM(G7:G9,(G10*-1)) -> 0 | H11: =SUM(H7:H9,(H10*-1)) -> 0 | I11: =SUM(I7:I9,(I10*-1)) -> 0 | J11: =SUM(J7:J9,(J10*-1)) -> 0 | K11: =SUM(K7:K9,(K10*-1)) -> 0 | ... O11: =SUM(O7:O9,(O10*-1)) -> 0 | P11: =SUM(Revenue[[#Totals],[Jan-26]:[Dec-26]]) -> 0
B12: Funds Available Before Expenses | C12: =(C4+Revenue[[#Totals],[ ]]) -> 0 | D12: =(D4+Revenue[[#Totals],[Jan-26]]) -> 0 | E12: =(E4+Revenue[[#Totals],[Feb-26]]) -> 0 | F12: =(F4+Revenue[[#Totals],[Mar-26]]) -> 0 | G12: =(G4+Revenue[[#Totals],[Apr-26]]) -> 0 | H12: =(H4+Revenue[[#Totals],[May-26]]) -> 0 | I12: =(I4+Revenue[[#Totals],[Jun-26]]) -> 0 | J12: =(J4+Revenue[[#Totals],[Jul-26]]) -> 0 | K12: =(K4+Revenue[[#Totals],[Aug-26]]) -> 0 | L12: =(L4+Revenue[[#Totals],[Sep-26]]) -> 0 | M12: =(M4+Revenue[[#Totals],[Oct-26]]) -> 0 | N12: =(N4+Revenue[[#Totals],[Nov-26]]) -> 0 | O12: =(O4+Revenue[[#Totals],[Dec-26]]) -> 0
B14: Expenses | D14: Jan-26 | E14: Feb-26 | F14: Mar-26 | G14: Apr-26 | H14: May-26 | I14: Jun-26 | J14: Jul-26 | K14: Aug-26 | L14: Sep-26 | M14: Oct-26 | N14: Nov-26 | O14: Dec-26 | P14: Total
B15: Invoices | D15: =JanInvoice[[#Totals],[Amount]] -> 0 | E15: =FebInvoice[[#Totals],[Amount]] -> 0 | F15: =MarInvoice[[#Totals],[Amount]] -> 0 | G15: =AprInvoice[[#Totals],[Amount]] -> 0 | H15: =MayInvoice[[#Totals],[Amount]] -> 0 | I15: =JunInvoice[[#Totals],[Amount]] -> 0 | J15: =JulInvoice[[#Totals],[Amount]] -> 0 | K15: =AugInvoice[[#Totals],[Amount]] -> 0 | L15: =SepInvoice[[#Totals],[Amount]] -> 0 | M15: =OctInvoice[[#Totals],[Amount]] -> 0 | N15: =NovInvoice[[#Totals],[Amount]] -> 0 | O15: =DecInvoice[[#Totals],[Amount]] -> 0 | P15: =SUM(Expenses[[#This Row],[Jan-26]:[Dec-26]]) -> 0
B16: Rent | D16: =January!I3 -> 0 | E16: =February!I3 -> 0 | F16: =March!I3 -> 0 | G16: =April!I3 -> 0 | H16: =May!I3 -> 0 | I16: =June!I3 -> 0 | J16: =July!I3 -> 0 | K16: =August!I3 -> 0 | L16: =September!I3 -> 0 | M16: =October!I3 -> 0 | N16: =November!I3 -> 0 | O16: =December!I3 -> 0 | P16: =SUM(Expenses[[#This Row],[Jan-26]:[Dec-26]]) -> 0
B17: Bills | D17: {=JanBillsTo[Bills*]} -> 0 | E17: {=FebBillsTo[Bills*]} -> 0 | F17: {=MarBillsTo[Bills*]} -> 0 | G17: {=AprBillsTo[Bills*]} -> 0 | H17: {=MayBillsTo[Bills*]} -> 0 | I17: {=JunBillsTo[Bills*]} -> 0 | J17: {=JulBillsTo[Bills*]} -> 0 | K17: {=AugBillsTo[Bills*]} -> 0 | L17: {=SepBillsTo[Bills*]} -> 0 | M17: {=OctBillsTo[Bills*]} -> 0 | N17: {=NovBillsTo[Bills*]} -> 0 | O17: {=DecBillsTo[Bills*]} -> 0 | P17: =SUM(Expenses[[#This Row],[Jan-26]:[Dec-26]]) -> 0
B18: Social Insurance Contributions | D18: =January!I6 -> 0 | E18: =February!I6 -> 0 | F18: =March!I6 -> 0 | G18: =April!I6 -> 0 | H18: =May!I6 -> 0 | I18: =June!I6 -> 0 | J18: =July!I6 -> 0 | K18: =August!I6 -> 0 | L18: =September!I6 -> 0 | M18: =October!I6 -> 0 | N18: =November!I6 -> 0 | O18: =December!I6 -> 0 | P18: =SUM(Expenses[[#This Row],[Jan-26]:[Dec-26]]) -> 0
B19: Accountancy Fees | D19: =January!I7 -> 0 | E19: =February!I7 -> 0 | F19: =March!I7 -> 0 | G19: =April!I7 -> 0 | H19: =May!I7 -> 0 | I19: =June!I7 -> 0 | J19: =July!I7 -> 0 | K19: =August!I7 -> 0 | L19: =September!I7 -> 0 | M19: =October!I7 -> 0 | N19: =November!I7 -> 0 | O19: =December!I7 -> 0 | P19: =SUM(Expenses[[#This Row],[Jan-26]:[Dec-26]]) -> 0
B20: VAT | D20: =January!I8 -> 0 | E20: =February!I8 -> 0 | F20: =March!I8 -> 0 | G20: =April!I8 -> 0 | H20: =May!I8 -> 0 | I20: =June!I8 -> 0 | J20: =July!I8 -> 0 | K20: =August!I8 -> 0 | L20: =September!I8 -> 0 | M20: =October!I8 -> 0 | N20: =November!I8 -> 0 | O20: =December!I8 -> 0 | P20: =SUM(Expenses[[#This Row],[Jan-26]:[Dec-26]]) -> 0
B21: Taxes / Levies | D21: =January!I9 -> 0 | E21: =February!I9 -> 0 | F21: =March!I9 -> 0 | G21: =April!I9 -> 0 | H21: =May!I9 -> 0 | I21: =June!I9 -> 0 | J21: =July!I9 -> 0 | K21: =August!I9 -> 0 | L21: =September!I9 -> 0 | M21: =October!I9 -> 0 | N21: =November!I9 -> 0 | O21: =December!I9 -> 0 | P21: =SUM(Expenses[[#This Row],[Jan-26]:[Dec-26]]) -> 0
B22: Other Expenses | D22: =January!I10 -> 0 | E22: =February!I10 -> 0 | F22: =March!I10 -> 0 | G22: =April!I10 -> 0 | H22: =May!I10 -> 0 | I22: =June!I10 -> 0 | J22: =July!I10 -> 0 | K22: =August!I10 -> 0 | L22: =September!I10 -> 0 | M22: =October!I10 -> 0 | N22: =November!I10 -> 0 | O22: =December!I10 -> 0 | P22: =SUM(Expenses[[#This Row],[Jan-26]:[Dec-26]]) -> 0
B23: Total Expenses | D23: =SUM(Expenses[Jan-26]) -> 0 | E23: =SUM(Expenses[Feb-26]) -> 0 | F23: =SUM(Expenses[Mar-26]) -> 0 | G23: =SUM(Expenses[Apr-26]) -> 0 | H23: =SUM(Expenses[May-26]) -> 0 | I23: =SUM(Expenses[Jun-26]) -> 0 | J23: =SUM(Expenses[Jul-26]) -> 0 | K23: =SUM(Expenses[Aug-26]) -> 0 | L23: =SUM(Expenses[Sep-26]) -> 0 | M23: =SUM(Expenses[Oct-26]) -> 0 | N23: =SUM(Expenses[Nov-26]) -> 0 | O23: =SUM(Expenses[Dec-26]) -> 0 | P23: =SUM(Expenses[[#Totals],[Jan-26]:[Dec-26]]) -> 0
B26: Closing Balance | C26: =C12 -> 0 | D26: =D12-Expenses[[#Totals],[Jan-26]] -> 0 | E26: =E12-Expenses[[#Totals],[Feb-26]] -> 0 | F26: =F12-Expenses[[#Totals],[Mar-26]] -> 0 | G26: =G12-Expenses[[#Totals],[Apr-26]] -> 0 | H26: =H12-Expenses[[#Totals],[May-26]] -> 0 | I26: =I12-Expenses[[#Totals],[Jun-26]] -> 0 | J26: =J12-Expenses[[#Totals],[Jul-26]] -> 0 | K26: =K12-Expenses[[#Totals],[Aug-26]] -> 0 | L26: =L12-Expenses[[#Totals],[Sep-26]] -> 0 | M26: =M12-Expenses[[#Totals],[Oct-26]] -> 0 | N26: =N12-Expenses[[#Totals],[Nov-26]] -> 0 | O26: =O12-Expenses[[#Totals],[Dec-26]] -> 0

Sheet January
B2: January | C2: Daily Cash Takings | D2: E-POS | E2: POS | F2: Refunds | H2: January Bills | I2: Amount | K2: Invoices | L2: Amount
B3: 1 | H3: Rent | K3: Northstar Office Supplies Ltd
B4: 2 | H4: Electricity* | K4: Metro Equipment Services Ltd
B5: 3 | H5: Telephone* | K5: Greenfield Stock & Supplies Ltd
B6: 4 | H6: Social Insurance Contributions | K6: Oakbridge Business Supplies Ltd
B7: 5 | H7: Accountancy Fees | K7: 5
B8: 6 | H8: VAT | K8: 6
B9: 7 | H9: Taxes / Levies | K9: 7
B10: 8 | H10: Other Expenses | K10: 8
B11: 9 | K11: 9
B12: 10 | H12: Bills* | K12: 10
B13: 11 | H13: =SUM(I4:I5) -> 0 | K13: 11
B14: 12 | K14: 12
B15: 13 | K15: 13
B16: 14 | K16: 14
B17: 15 | K17: 15
B18: 16 | K18: 16
B19: 17 | K19: 17
B20: 18 | K20: 18
B21: 19 | K21: 19
B22: 20 | K22: 20
B23: 21 | K23: Total | L23: =SUBTOTAL(109,JanInvoice[Amount]) -> 0
B24: 22
B25: 23
B26: 24
B27: 25
B28: 26
B29: 27
B30: 28
B31: 29
B32: 30
B33: 31
B34: Total | C34: =SUM(C3:C33) -> 0 | D34: =SUM(D3:D33) -> 0 | E34: =SUM(E3:E33) -> 0 | F34: =SUM(F3:F33) -> 0

Sheet February
B2: February | C2: Daily Cash Takings | D2: E-POS | E2: POS | F2: Refunds | H2: February Bills | I2: Amount | K2: Invoices | L2: Amount
B3: 1 | H3: Rent | K3: Northstar Office Supplies Ltd
B4: 2 | H4: Electricity* | K4: Metro Equipment Services Ltd
B5: 3 | H5: Telephone* | K5: Greenfield Stock & Supplies Ltd
B6: 4 | H6: Social Insurance Contributions | K6: Oakbridge Business Supplies Ltd
B7: 5 | H7: Accountancy Fees | K7: 5
B8: 6 | H8: VAT | K8: 6
B9: 7 | H9: Taxes / Levies | K9: 7
B10: 8 | H10: Other Expenses | K10: 8
B11: 9 | K11: 9
B12: 10 | H12: Bills* | K12: 10
B13: 11 | H13: =SUM(I4:I5) -> 0 | K13: 11
B14: 12 | K14: 12
B15: 13 | K15: 13
B16: 14 | K16: 14
B17: 15 | K17: 15
B18: 16 | K18: 16
B19: 17 | K19: 17
B20: 18 | K20: 18
B21: 19 | K21: 19
B22: 20 | K22: 20
B23: 21 | K23: Total | L23: =SUBTOTAL(109,FebInvoice[Amount]) -> 0
B24: 22
B25: 23
B26: 24
B27: 25
B28: 26
B29: 27
B30: 28
B31: 29
B32: 30
B33: 31
B34: Total | C34: =SUM(C3:C33) -> 0 | D34: =SUM(D3:D33) -> 0 | E34: =SUM(E3:E33) -> 0 | F34: =SUM(F3:F33) -> 0

Sheet March
B2: March | C2: Daily Cash Takings | D2: E-POS | E2: POS | F2: Refunds | H2: March Bills | I2: Amount | K2: Invoices | L2: Amount
B3: 1 | H3: Rent | K3: Northstar Office Supplies Ltd
B4: 2 | H4: Electricity* | K4: Metro Equipment Services Ltd
B5: 3 | H5: Telephone* | K5: Greenfield Stock & Supplies Ltd
B6: 4 | H6: Social Insurance Contributions | K6: Oakbridge Business Supplies Ltd
B7: 5 | H7: Accountancy Fees | K7: 5
B8: 6 | H8: VAT | K8: 6
B9: 7 | H9: Taxes / Levies | K9: 7
B10: 8 | H10: Other Expenses | K10: 8
B11: 9 | K11: 9
B12: 10 | H12: Bills* | K12: 10
B13: 11 | H13: =SUM(I4:I5) -> 0 | K13: 11
B14: 12 | K14: 12
B15: 13 | K15: 13
B16: 14 | K16: 14
B17: 15 | K17: 15
B18: 16 | K18: 16
B19: 17 | K19: 17
B20: 18 | K20: 18
B21: 19 | K21: 19
B22: 20 | K22: 20
B23: 21 | K23: Total | L23: =SUBTOTAL(109,MarInvoice[Amount]) -> 0
B24: 22
B25: 23
B26: 24
B27: 25
B28: 26
B29: 27
B30: 28
B31: 29
B32: 30
B33: 31
B34: Total | C34: =SUM(C3:C33) -> 0 | D34: =SUM(D3:D33) -> 0 | E34: =SUM(E3:E33) -> 0 | F34: =SUM(F3:F33) -> 0

Sheet April
B2: April | C2: Daily Cash Takings | D2: E-POS | E2: POS | F2: Refunds | H2: April Bills | I2: Amount | K2: Invoices | L2: Amount
B3: 1 | H3: Rent | K3: Northstar Office Supplies Ltd
B4: 2 | H4: Electricity* | K4: Metro Equipment Services Ltd
B5: 3 | H5: Telephone* | K5: Greenfield Stock & Supplies Ltd
B6: 4 | H6: Social Insurance Contributions | K6: Oakbridge Business Supplies Ltd
B7: 5 | H7: Accountancy Fees | K7: 5
B8: 6 | H8: VAT | K8: 6
B9: 7 | H9: Taxes / Levies | K9: 7
B10: 8 | H10: Other Expenses | K10: 8
B11: 9 | K11: 9
B12: 10 | H12: Bills* | K12: 10
B13: 11 | H13: =SUM(I4:I5) -> 0 | K13: 11
B14: 12 | K14: 12
B15: 13 | K15: 13
B16: 14 | K16: 14
B17: 15 | K17: 15
B18: 16 | K18: 16
B19: 17 | K19: 17
B20: 18 | K20: 18
B21: 19 | K21: 19
B22: 20 | K22: 20
B23: 21 | K23: Total | L23: =SUBTOTAL(109,AprInvoice[Amount]) -> 0
B24: 22
B25: 23
B26: 24
B27: 25
B28: 26
B29: 27
B30: 28
B31: 29
B32: 30
B33: 31
B34: Total | C34: =SUM(C3:C33) -> 0 | D34: =SUM(D3:D33) -> 0 | E34: =SUM(E3:E33) -> 0 | F34: =SUM(F3:F33) -> 0

Sheet May
B2: May | C2: Daily Cash Takings | D2: E-POS | E2: POS | F2: Refunds | H2: May Bills | I2: Amount | K2: invoices | L2: Amount
B3: 1 | H3: Rent | K3: Northstar Office Supplies Ltd
B4: 2 | H4: Electricity* | K4: Metro Equipment Services Ltd
B5: 3 | H5: Telephone* | K5: Greenfield Stock & Supplies Ltd
B6: 4 | H6: Social Insurance Contributions | K6: Oakbridge Business Supplies Ltd
B7: 5 | H7: Accountancy Fees | K7: 5
B8: 6 | H8: VAT | K8: 6
B9: 7 | H9: Taxes / Levies | K9: 7
B10: 8 | H10: Other Expenses | K10: 8
B11: 9 | K11: 9
B12: 10 | H12: Bills* | K12: 10
B13: 11 | H13: =SUM(I4:I5) -> 0 | K13: 11
B14: 12 | K14: 12
B15: 13 | K15: 13
B16: 14 | K16: 14
B17: 15 | K17: 15
B18: 16 | K18: 16
B19: 17 | K19: 17
B20: 18 | K20: 18
B21: 19 | K21: 19
B22: 20 | K22: 20
B23: 21 | K23: Total | L23: =SUBTOTAL(109,MayInvoice[Amount]) -> 0
B24: 22
B25: 23
B26: 24
B27: 25
B28: 26
B29: 27
B30: 28
B31: 29
B32: 30
B33: 31
B34: Total | C34: =SUM(C3:C33) -> 0 | D34: =SUM(D3:D33) -> 0 | E34: =SUM(E3:E33) -> 0 | F34: =SUM(F3:F33) -> 0

Sheet June
B2: June | C2: Daily Cash Takings | D2: E-POS | E2: POS | F2: Refunds | H2: June Bills | I2: Amount | K2: Invoices | L2: Amount
B3: 1 | H3: Rent | K3: Northstar Office Supplies Ltd
B4: 2 | H4: Electricity* | K4: Metro Equipment Services Ltd
B5: 3 | H5: Telephone* | K5: Greenfield Stock & Supplies Ltd
B6: 4 | H6: Social Insurance Contributions | K6: Oakbridge Business Supplies Ltd
B7: 5 | H7: Accountancy Fees | K7: 5
B8: 6 | H8: VAT | K8: 6
B9: 7 | H9: Taxes / Levies | K9: 7
B10: 8 | H10: Other Expenses | K10: 8
B11: 9 | K11: 9
B12: 10 | H12: Bills* | K12: 10
B13: 11 | H13: =SUM(I4:I5) -> 0 | K13: 11
B14: 12 | K14: 12
B15: 13 | K15: 13
B16: 14 | K16: 14
B17: 15 | K17: 15
B18: 16 | K18: 16
B19: 17 | K19: 17
B20: 18 | K20: 18
B21: 19 | K21: 19
B22: 20 | K22: 20
B23: 21 | K23: Total | L23: =SUBTOTAL(109,JunInvoice[Amount]) -> 0
B24: 22
B25: 23
B26: 24
B27: 25
B28: 26
B29: 27
B30: 28
B31: 29
B32: 30
B33: 31
B34: Total | C34: =SUM(C3:C33) -> 0 | D34: =SUM(D3:D33) -> 0 | E34: =SUM(E3:E33) -> 0 | F34: =SUM(F3:F33) -> 0

Sheet July
B2: July | C2: Daily Cash Takings | D2: E-POS | E2: POS | F2: Refunds | H2: July Bills | I2: Amount | K2: Invoices | L2: Amount
B3: 7 | H3: Rent | K3: Northstar Office Supplies Ltd
B4: 2 | H4: Electricity* | K4: Metro Equipment Services Ltd
B5: 3 | H5: Telephone* | K5: Greenfield Stock & Supplies Ltd
B6: 4 | H6: Social Insurance Contributions | K6: Oakbridge Business Supplies Ltd
B7: 5 | H7: Accountancy Fees | K7: 5
B8: 6 | H8: VAT | K8: 6
B9: 7 | H9: Taxes / Levies | K9: 7
B10: 8 | H10: Other Expenses | K10: 8
B11: 9 | K11: 9
B12: 10 | H12: Bills* | K12: 10
B13: 11 | H13: =SUM(I4:I5) -> 0 | K13: 11
B14: 12 | K14: 12
B15: 13 | K15: 13
B16: 14 | K16: 14
B17: 15 | K17: 15
B18: 16 | K18: 16
B19: 17 | K19: 17
B20: 18 | K20: 18
B21: 19 | K21: 19
B22: 20 | K22: 20
B23: 21 | K23: Total | L23: =SUBTOTAL(109,JulInvoice[Amount]) -> 0
B24: 22
B25: 23
B26: 24
B27: 25
B28: 26
B29: 27
B30: 28
B31: 29
B32: 30
B33: 31
B34: Total | C34: =SUM(C3:C33) -> 0 | D34: =SUM(D3:D33) -> 0 | E34: =SUM(E3:E33) -> 0 | F34: =SUM(F3:F33) -> 0

Sheet August
B2: August | C2: Daily Cash Takings | D2: E-POS | E2: POS | F2: Refunds | H2: August Bills | I2: Amount | K2: Invoices | L2: Amount
B3: 1 | H3: Rent | K3: Northstar Office Supplies Ltd
B4: 2 | H4: Electricity* | K4: Metro Equipment Services Ltd
B5: 3 | H5: Telephone* | K5: Greenfield Stock & Supplies Ltd
B6: 4 | H6: Social Insurance Contributions | K6: Oakbridge Business Supplies Ltd
B7: 5 | H7: Accountancy Fees | K7: 5
B8: 6 | H8: VAT | K8: 6
B9: 7 | H9: Taxes / Levies | K9: 7
B10: 8 | H10: Other Expenses | K10: 8
B11: 9 | K11: 9
B12: 10 | H12: Bills* | K12: 10
B13: 11 | H13: =SUM(I4:I5) -> 0 | K13: 11
B14: 12 | K14: 12
B15: 13 | K15: 13
B16: 14 | K16: 14
B17: 15 | K17: 15
B18: 16 | K18: 16
B19: 17 | K19: 17
B20: 18 | K20: 18
B21: 19 | K21: 19
B22: 20 | K22: 20
B23: 21 | K23: Total | L23: =SUBTOTAL(109,AugInvoice[Amount]) -> 0
B24: 22
B25: 23
B26: 24
B27: 25
B28: 26
B29: 27
B30: 28
B31: 29
B32: 30
B33: 31
B34: Total | C34: =SUM(C3:C33) -> 0 | D34: =SUM(D3:D33) -> 0 | E34: =SUM(E3:E33) -> 0 | F34: =SUM(F3:F33) -> 0

Sheet September
B2: September | C2: Daily Cash Takings | D2: E-POS | E2: POS | F2: Refunds | H2: September Bills | I2: Amount | K2: Invoices | L2: Amount
B3: 9 | H3: Rent | K3: Northstar Office Supplies Ltd
B4: 2 | H4: Electricity* | K4: Metro Equipment Services Ltd
B5: 3 | H5: Telephone* | K5: Greenfield Stock & Supplies Ltd
B6: 4 | H6: Social Insurance Contributions | K6: Oakbridge Business Supplies Ltd
B7: 5 | H7: Accountancy Fees | K7: 5
B8: 6 | H8: VAT | K8: 6
B9: 7 | H9: Taxes / Levies | K9: 7
B10: 8 | H10: Other Expenses | K10: 8
B11: 9 | K11: 9
B12: 10 | H12: Bills* | K12: 10
B13: 11 | H13: =SUM(I4:I5) -> 0 | K13: 11
B14: 12 | K14: 12
B15: 13 | K15: 13
B16: 14 | K16: 14
B17: 15 | K17: 15
B18: 16 | K18: 16
B19: 17 | K19: 17
B20: 18 | K20: 18
B21: 19 | K21: 19
B22: 20 | K22: 20
B23: 21 | K23: Total | L23: =SUBTOTAL(109,SepInvoice[Amount]) -> 0
B24: 22
B25: 23
B26: 24
B27: 25
B28: 26
B29: 27
B30: 28
B31: 29
B32: 30
B33: 31
B34: Total | C34: =SUM(C3:C33) -> 0 | D34: =SUM(D3:D33) -> 0 | E34: =SUM(E3:E33) -> 0 | F34: =SUM(F3:F33) -> 0

Sheet October
B2: October | C2: Daily Cash Takings | D2: E-POS | E2: POS | F2: Refunds | H2: October Bills | I2: Amount | K2: Invoices | L2: Amount
B3: 1 | H3: Rent | K3: Northstar Office Supplies Ltd
B4: 2 | H4: Electricity* | K4: Metro Equipment Services Ltd
B5: 3 | H5: Telephone* | K5: Greenfield Stock & Supplies Ltd
B6: 4 | H6: Social Insurance Contributions | K6: Oakbridge Business Supplies Ltd
B7: 5 | H7: Accountancy Fees | K7: 5
B8: 6 | H8: VAT | K8: 6
B9: 7 | H9: Taxes / Levies | K9: 7
B10: 8 | H10: Other Expenses | K10: 8
B11: 9 | K11: 9
B12: 10 | H12: Bills* | K12: 10
B13: 11 | H13: =SUM(I4:I5) -> 0 | K13: 11
B14: 12 | K14: 12
B15: 13 | K15: 13
B16: 14 | K16: 14
B17: 15 | K17: 15
B18: 16 | K18: 16
B19: 17 | K19: 17
B20: 18 | K20: 18
B21: 19 | K21: 19
B22: 20 | K22: 20
B23: 21 | K23: Total | L23: =SUBTOTAL(109,OctInvoice[Amount]) -> 0
B24: 22
B25: 23
B26: 24
B27: 25
B28: 26
B29: 27
B30: 28
B31: 29
B32: 30
B33: 31
B34: Total | C34: =SUM(C3:C33) -> 0 | D34: =SUM(D3:D33) -> 0 | E34: =SUM(E3:E33) -> 0 | F34: =SUM(F3:F33) -> 0

Sheet November
B2: November | C2: Daily Cash Takings | D2: E-POS | E2: POS | F2: Refunds | H2: November Bills | I2: Amount | K2: Invoices | L2: Amount
B3: 1 | H3: Rent | K3: Northstar Office Supplies Ltd
B4: 2 | H4: Electricity* | K4: Metro Equipment Services Ltd
B5: 3 | H5: Telephone* | K5: Greenfield Stock & Supplies Ltd
B6: 4 | H6: Social Insurance Contributions | K6: Oakbridge Business Supplies Ltd
B7: 5 | H7: Accountancy Fees | K7: 5
B8: 6 | H8: VAT | K8: 6
B9: 7 | H9: Taxes / Levies | K9: 7
B10: 8 | H10: Other Expenses | K10: 8
B11: 9 | K11: 9
B12: 10 | H12: Bills* | K12: 10
B13: 11 | H13: =SUM(I4:I5) -> 0 | K13: 11
B14: 12 | K14: 12
B15: 13 | K15: 13
B16: 14 | K16: 14
B17: 15 | K17: 15
B18: 16 | K18: 16
B19: 17 | K19: 17
B20: 18 | K20: 18
B21: 19 | K21: 19
B22: 20 | K22: 20
B23: 21 | K23: Total | L23: =SUBTOTAL(109,NovInvoice[Amount]) -> 0
B24: 22
B25: 23
B26: 24
B27: 25
B28: 26
B29: 27
B30: 28
B31: 29
B32: 30
B33: 31
B34: Total | C34: =SUM(C3:C33) -> 0 | D34: =SUM(D3:D33) -> 0 | E34: =SUM(E3:E33) -> 0 | F34: =SUM(F3:F33) -> 0

Sheet December
B2: December | C2: Daily Cash Takings | D2: E-POS | E2: POS | F2: Refunds | H2: December Bills | I2: Amount | K2: Invoices | L2: Amount
B3: 1 | H3: Rent | K3: Northstar Office Supplies Ltd
B4: 2 | H4: Electricity* | K4: Metro Equipment Services Ltd
B5: 3 | H5: Telephone* | K5: Greenfield Stock & Supplies Ltd
B6: 4 | H6: Social Insurance Contributions | K6: Oakbridge Business Supplies Ltd
B7: 5 | H7: Accountancy Fees | K7: 5
B8: 6 | H8: VAT | K8: 6
B9: 7 | H9: Taxes / Levies | K9: 7
B10: 8 | H10: Other Expenses | K10: 8
B11: 9 | K11: 9
B12: 10 | H12: Bills* | K12: 10
B13: 11 | H13: =SUM(I4:I5) -> 0 | K13: 11
B14: 12 | K14: 12
B15: 13 | K15: 13
B16: 14 | K16: 14
B17: 15 | K17: 15
B18: 16 | K18: 16
B19: 17 | K19: 17
B20: 18 | K20: 18
B21: 19 | K21: 19
B22: 20 | K22: 20
B23: 21 | K23: Total | L23: =SUBTOTAL(109,DecInvoice[Amount]) -> 0
B24: 22
B25: 23
B26: 24
B27: 25
B28: 26
B29: 27
B30: 28
B31: 29
B32: 30
B33: 31
B34: Total | C34: =SUM(C3:C33) -> 0 | D34: =SUM(D3:D33) -> 0 | E34: =SUM(E3:E33) -> 0 | F34: =SUM(F3:F33) -> 0
